Metadata-Version: 2.1
Name: regression_aya_hamdi
Version: 1.0.0
Summary:  simple linear regression pakcage
Home-page: http://pypi.python.org/pypi/regression/
Author: hamdi aya
Author-email: ay.hamdi@esi-sba.dz
License: LICENSE.txt
License-File: LICENSE.txt
Requires-Dist: regression_aya_hamdi
